grid_api/__init__.py
grid_api/_base_client.py
grid_api/_client.py
grid_api/_compat.py
grid_api/_constants.py
grid_api/_exceptions.py
grid_api/_files.py
grid_api/_models.py
grid_api/_qs.py
grid_api/_resource.py
grid_api/_response.py
grid_api/_streaming.py
grid_api/_types.py
grid_api/_version.py
grid_api/pagination.py
grid_api/py.typed
grid_api/_utils/__init__.py
grid_api/_utils/_compat.py
grid_api/_utils/_datetime_parse.py
grid_api/_utils/_logs.py
grid_api/_utils/_proxy.py
grid_api/_utils/_reflection.py
grid_api/_utils/_resources_proxy.py
grid_api/_utils/_streams.py
grid_api/_utils/_sync.py
grid_api/_utils/_transform.py
grid_api/_utils/_typing.py
grid_api/_utils/_utils.py
grid_api/lib/.keep
grid_api/resources/__init__.py
grid_api/resources/beta.py
grid_api/resources/workbooks.py
grid_api/types/__init__.py
grid_api/types/beta_get_workbook_labels_response.py
grid_api/types/beta_get_workbook_parameters_response.py
grid_api/types/beta_search_labels_params.py
grid_api/types/beta_search_labels_response.py
grid_api/types/workbook_calc_params.py
grid_api/types/workbook_calc_response.py
grid_api/types/workbook_export_params.py
grid_api/types/workbook_list_params.py
grid_api/types/workbook_list_response.py
grid_api/types/workbook_query_params.py
grid_api/types/workbook_query_response.py
grid_api/types/workbook_render_chart_params.py
grid_api/types/workbook_upload_params.py
grid_api/types/workbook_upload_response.py
grid_api/types/workbook_values_params.py
grid_api/types/workbook_values_response.py
grid_api-1.10.0.dist-info/METADATA
grid_api-1.10.0.dist-info/WHEEL
grid_api-1.10.0.dist-info/licenses/LICENSE
grid_api-1.10.0.dist-info/RECORD
